gen_changelog/__init__.py
gen_changelog/cli.py
gen_changelog-0.1.1.dist-info/entry_points.txt
gen_changelog-0.1.1.dist-info/LICENSE
gen_changelog-0.1.1.dist-info/WHEEL
gen_changelog-0.1.1.dist-info/METADATA
gen_changelog-0.1.1.dist-info/RECORD
